README.md
setup.cfg
setup.py
src/neuralkg_ind/__init__.py
src/neuralkg_ind.egg-info/PKG-INFO
src/neuralkg_ind.egg-info/SOURCES.txt
src/neuralkg_ind.egg-info/dependency_links.txt
src/neuralkg_ind.egg-info/requires.txt
src/neuralkg_ind.egg-info/top_level.txt
src/neuralkg_ind/data/DataPreprocess.py
src/neuralkg_ind/data/Grounding.py
src/neuralkg_ind/data/KGDataModule.py
src/neuralkg_ind/data/RuleDataLoader.py
src/neuralkg_ind/data/Sampler.py
src/neuralkg_ind/data/__init__.py
src/neuralkg_ind/data/base_data_module.py
src/neuralkg_ind/eval_task/__init__.py
src/neuralkg_ind/eval_task/link_prediction.py
src/neuralkg_ind/eval_task/triple_classification.py
src/neuralkg_ind/lit_model/BaseLitModel.py
src/neuralkg_ind/lit_model/CompGCNLitModel.py
src/neuralkg_ind/lit_model/ConvELitModel.py
src/neuralkg_ind/lit_model/CrossELitModel.py
src/neuralkg_ind/lit_model/IterELitModel.py
src/neuralkg_ind/lit_model/KBATLitModel.py
src/neuralkg_ind/lit_model/KGELitModel.py
src/neuralkg_ind/lit_model/MetaGNNLitModel.py
src/neuralkg_ind/lit_model/RGCNLitModel.py
src/neuralkg_ind/lit_model/RugELitModel.py
src/neuralkg_ind/lit_model/SEGNNLitModel.py
src/neuralkg_ind/lit_model/SNRILitModel.py
src/neuralkg_ind/lit_model/XTransELitModel.py
src/neuralkg_ind/lit_model/__init__.py
src/neuralkg_ind/lit_model/indGNNLitModel.py
src/neuralkg_ind/loss/Adv_Loss.py
src/neuralkg_ind/loss/ComplEx_NNE_AER_Loss.py
src/neuralkg_ind/loss/CrossE_Loss.py
src/neuralkg_ind/loss/Cross_Entropy_Loss.py
src/neuralkg_ind/loss/KBAT_Loss.py
src/neuralkg_ind/loss/Logsig_Loss.py
src/neuralkg_ind/loss/Margin_Loss.py
src/neuralkg_ind/loss/RGCN_Loss.py
src/neuralkg_ind/loss/RugE_Loss.py
src/neuralkg_ind/loss/SimplE_Loss.py
src/neuralkg_ind/loss/Softplus_Loss.py
src/neuralkg_ind/loss/__init__.py
src/neuralkg_ind/model/__init__.py
src/neuralkg_ind/model/GNNModel/CoMPILE.py
src/neuralkg_ind/model/GNNModel/CompGCN.py
src/neuralkg_ind/model/GNNModel/Grail.py
src/neuralkg_ind/model/GNNModel/KBAT.py
src/neuralkg_ind/model/GNNModel/MorsE.py
src/neuralkg_ind/model/GNNModel/RGCN.py
src/neuralkg_ind/model/GNNModel/RMPI.py
src/neuralkg_ind/model/GNNModel/SEGNN.py
src/neuralkg_ind/model/GNNModel/SNRI.py
