Metadata-Version: 2.1
Name: neuralkg-ind
Version: 1.0.0
Summary:  A Python Library for Inductive Knowledge Graph Representation Learning
Home-page: https://github.com/zjukg/NeuralKG-ind
Author: ZJUKG
Author-email: 22151303@zju.edu.cn
License: UNKNOWN
Platform: UNKNOWN
Classifier: Programming Language :: Python :: 3
Classifier: License :: OSI Approved :: MIT License
Classifier: Operating System :: OS Independent
Requires-Python: >=3.6
